README.rst
pyproject.toml
setup.py
bin/obz
obz/__init__.py
obz.egg-info/PKG-INFO
obz.egg-info/SOURCES.txt
obz.egg-info/dependency_links.txt
obz.egg-info/requires.txt
obz.egg-info/top_level.txt
obz/modules/__init__.py
obz/modules/dbg.py
obz/modules/err.py
obz/modules/flt.py
obz/modules/fnd.py
obz/modules/irc.py
obz/modules/llm.py
obz/modules/log.py
obz/modules/man.py
obz/modules/mbx.py
obz/modules/mdl.py
obz/modules/mod.py
obz/modules/req.py
obz/modules/rss.py
obz/modules/rst.py
obz/modules/slg.py
obz/modules/tbl.py
obz/modules/tdo.py
obz/modules/thr.py
obz/modules/tmr.py
obz/modules/udp.py
obz/modules/upt.py
obz/modules/ver.py
obz/modules/web.py
obz/modules/wsd.py