Metadata-Version: 2.1
Name: obz
Version: 121
Summary: OBZ
Author-email: Bart Thate <bthate@dds.nl>
License: Public Domain
Project-URL: home, https://pypi.org/project/obx
Project-URL: bugs, https://github.com/bthate/obx/issues
Project-URL: source, https://github.com/bthate/obx
Classifier: Development Status :: 1 - Planning
Classifier: License :: Public Domain
Classifier: Programming Language :: Python
Classifier: Intended Audience :: Developers
Classifier: Topic :: Software Development :: Libraries :: Python Modules
